{
  "meta": {
    "total_jobs": 110,
    "timestamp": "2025-03-30T23:14:33.595907"
  },
  "jobs": [
    {
      "title": "Stores Assistant",
      "company": "Cenmetrix",
      "location": "Colombo, Western Province, Sri Lanka",
      "posted_date": "5 days ago",
      "job_url": "https://lk.linkedin.com/jobs/view/stores-assistant-at-cenmetrix-4192884249?position=1&pageNum=0&refId=s7V7mSX5gk4u6asyU2%2Bizg%3D%3D&trackingId=xVe%2F7ortrUL3PvTXO0bNBw%3D%3D",
      "listing_id": "urn:li:jobPosting:4192884249"
    },
    {
      "title": "Civic Centre - Casual Positions",
      "company": "Shire of Broome",
      "location": "Civic Centre, Northern Province, Sri Lanka",
      "posted_date": "1 month ago",
      "job_url": "https://lk.linkedin.com/jobs/view/civic-centre-casual-positions-at-shire-of-broome-4157857769?position=2&pageNum=0&refId=s7V7mSX5gk4u6asyU2%2Bizg%3D%3D&trackingId=%2B1IVQzszYV%2BHJ0htP2HvcQ%3D%3D",
      "listing_id": "urn:li:jobPosting:4157857769"
    },
    {
      "title": "Sinhala OPI/VRI Interpretation Vacancy (Remote)",
      "company": "Kalamcx",
      "location": "Colombo, Western Province, Sri Lanka",
      "posted_date": "1 year ago",
      "job_url": "https://lk.linkedin.com/jobs/view/sinhala-opi-vri-interpretation-vacancy-remote-at-kalamcx-3801934334?position=3&pageNum=0&refId=s7V7mSX5gk4u6asyU2%2Bizg%3D%3D&trackingId=Zw%2B%2Ffu4GVrat0fHAuKE5sQ%3D%3D",
      "listing_id": "urn:li:jobPosting:3801934334"
    },
    {
      "title": "Management Trainee - Online Marketing (Remote)",
      "company": "EKWA MARKETING.",
      "location": "Sri Lanka",
      "posted_date": "1 month ago",
      "job_url": "https://lk.linkedin.com/jobs/view/management-trainee-online-marketing-remote-at-ekwa-marketing-4167869900?position=4&pageNum=0&refId=s7V7mSX5gk4u6asyU2%2Bizg%3D%3D&trackingId=v%2FjTxnO8XUnSnJC3ec%2BGrw%3D%3D",
      "listing_id": "urn:li:jobPosting:4167869900"
    },
    {
      "title": "Assistant Accountant",
      "company": "AuroraRCM",
      "location": "Colombo, Western Province, Sri Lanka",
      "posted_date": "1 month ago",
      "job_url": "https://lk.linkedin.com/jobs/view/assistant-accountant-at-aurorarcm-4142499682?position=5&pageNum=0&refId=s7V7mSX5gk4u6asyU2%2Bizg%3D%3D&trackingId=%2FhZSPeWROS4farqsoOO8sw%3D%3D",
      "listing_id": "urn:li:jobPosting:4142499682"
    },
    {
      "title": "Sinhala VRI/OPI Interpretation Vacancy - Kandy",
      "company": "Kalamcx",
      "location": "kandy, Central Province, Sri Lanka",
      "posted_date": "9 months ago",
      "job_url": "https://lk.linkedin.com/jobs/view/sinhala-vri-opi-interpretation-vacancy-kandy-at-kalamcx-3953542264?position=6&pageNum=0&refId=s7V7mSX5gk4u6asyU2%2Bizg%3D%3D&trackingId=74Qlf0Sk7BdouaupaKpW2Q%3D%3D",
      "listing_id": "urn:li:jobPosting:3953542264"
    },
    {
      "title": "Medical Typist – Histology",
      "company": "Awanui Group",
      "location": "Badulla District, Uva Province, Sri Lanka",
      "posted_date": "5 days ago",
      "job_url": "https://lk.linkedin.com/jobs/view/medical-typist-%E2%80%93-histology-at-awanui-group-4192470206?position=7&pageNum=0&refId=s7V7mSX5gk4u6asyU2%2Bizg%3D%3D&trackingId=ekGMuM5RFb2gx%2BcSkZwF2A%3D%3D",
      "listing_id": "urn:li:jobPosting:4192470206"
    },
    {
      "title": "General Application",
      "company": "AuroraRCM",
      "location": "Colombo, Western Province, Sri Lanka",
      "posted_date": "1 month ago",
      "job_url": "https://lk.linkedin.com/jobs/view/general-application-at-aurorarcm-4169924275?position=8&pageNum=0&refId=s7V7mSX5gk4u6asyU2%2Bizg%3D%3D&trackingId=SIrDgMJarXJPGrJVT8JUbg%3D%3D",
      "listing_id": "urn:li:jobPosting:4169924275"
    },
    {
      "title": "SR QA Manual (LEVEL 3) - Remote, Sri Lanka",
      "company": "Agnos Inc.",
      "location": "Sri Lanka",
      "posted_date": "2 months ago",
      "job_url": "https://lk.linkedin.com/jobs/view/sr-qa-manual-level-3-remote-sri-lanka-at-agnos-inc-4118742518?position=9&pageNum=0&refId=s7V7mSX5gk4u6asyU2%2Bizg%3D%3D&trackingId=dVZKHx%2F2s9yrPfotZAtIrQ%3D%3D",
      "listing_id": "urn:li:jobPosting:4118742518"
    },
    {
      "title": "Frontend Developer",
      "company": "Dijital Team",
      "location": "Colombo, Western Province, Sri Lanka",
      "posted_date": "3 weeks ago",
      "job_url": "https://lk.linkedin.com/jobs/view/frontend-developer-at-dijital-team-4171864209?position=10&pageNum=0&refId=s7V7mSX5gk4u6asyU2%2Bizg%3D%3D&trackingId=2K0b8Cmnki9BbuP0nPqWrA%3D%3D",
      "listing_id": "urn:li:jobPosting:4171864209"
    },
    {
      "title": "People and Culture Administrator",
      "company": "Dijital Team",
      "location": "Colombo, Western Province, Sri Lanka",
      "posted_date": "3 weeks ago",
      "job_url": "https://lk.linkedin.com/jobs/view/people-and-culture-administrator-at-dijital-team-4174096580?position=11&pageNum=0&refId=s7V7mSX5gk4u6asyU2%2Bizg%3D%3D&trackingId=EYcXE5eUIV1O0SrQGwdVAg%3D%3D",
      "listing_id": "urn:li:jobPosting:4174096580"
    },
    {
      "title": "SSR QA Manual (LEVEL 2) - Remote, Sri Lanka",
      "company": "Agnos Inc.",
      "location": "Sri Lanka",
      "posted_date": "2 months ago",
      "job_url": "https://lk.linkedin.com/jobs/view/ssr-qa-manual-level-2-remote-sri-lanka-at-agnos-inc-4118749500?position=12&pageNum=0&refId=s7V7mSX5gk4u6asyU2%2Bizg%3D%3D&trackingId=6IQ6rxhtnKIczPn50jYIHQ%3D%3D",
      "listing_id": "urn:li:jobPosting:4118749500"
    },
    {
      "title": "SR QA Manual (LEVEL 3) - Remote, Sri Lanka",
      "company": "Agnos Inc.",
      "location": "Sri Lanka",
      "posted_date": "2 months ago",
      "job_url": "https://lk.linkedin.com/jobs/view/sr-qa-manual-level-3-remote-sri-lanka-at-agnos-inc-4118737910?position=13&pageNum=0&refId=s7V7mSX5gk4u6asyU2%2Bizg%3D%3D&trackingId=dnwvjsW%2BcOoC4SkGJf%2FUGw%3D%3D",
      "listing_id": "urn:li:jobPosting:4118737910"
    },
    {
      "title": "SSR QA Manual (LEVEL 2) - Remote, Sri Lanka",
      "company": "Agnos Inc.",
      "location": "Sri Lanka",
      "posted_date": "2 months ago",
      "job_url": "https://lk.linkedin.com/jobs/view/ssr-qa-manual-level-2-remote-sri-lanka-at-agnos-inc-4118748613?position=14&pageNum=0&refId=s7V7mSX5gk4u6asyU2%2Bizg%3D%3D&trackingId=kkWj8FjV2D7HIeVkJoxU%2Fw%3D%3D",
      "listing_id": "urn:li:jobPosting:4118748613"
    },
    {
      "title": "Assistant Manager – Workplace Services",
      "company": "Unilever",
      "location": "Horana, Western Province, Sri Lanka",
      "posted_date": "2 weeks ago",
      "job_url": "https://lk.linkedin.com/jobs/view/assistant-manager-%E2%80%93-workplace-services-at-unilever-4181427769?position=15&pageNum=0&refId=s7V7mSX5gk4u6asyU2%2Bizg%3D%3D&trackingId=WCMm%2FQCxaaJX1Afhjq830g%3D%3D",
      "listing_id": "urn:li:jobPosting:4181427769"
    },
    {
      "title": "Full Stack Web Developer – Intern",
      "company": "DoMedia",
      "location": "Colombo, Western Province, Sri Lanka",
      "posted_date": "2 months ago",
      "job_url": "https://lk.linkedin.com/jobs/view/full-stack-web-developer-%E2%80%93-intern-at-domedia-4127917718?position=16&pageNum=0&refId=s7V7mSX5gk4u6asyU2%2Bizg%3D%3D&trackingId=7hXQJOxvhVffZJjRVGMUJw%3D%3D",
      "listing_id": "urn:li:jobPosting:4127917718"
    },
    {
      "title": "Executive - Human Resources",
      "company": "Perfetti Van Melle",
      "location": "Rajagiriya, Western Province, Sri Lanka",
      "posted_date": "2 weeks ago",
      "job_url": "https://lk.linkedin.com/jobs/view/executive-human-resources-at-perfetti-van-melle-4182292830?position=17&pageNum=0&refId=s7V7mSX5gk4u6asyU2%2Bizg%3D%3D&trackingId=fLTv30Cw89f32tbUwBL%2FQQ%3D%3D",
      "listing_id": "urn:li:jobPosting:4182292830"
    },
    {
      "title": "Executive Partner to the Founder/CEO",
      "company": "Hyperon",
      "location": "Sri Lanka",
      "posted_date": "1 month ago",
      "job_url": "https://lk.linkedin.com/jobs/view/executive-partner-to-the-founder-ceo-at-hyperon-4167558532?position=18&pageNum=0&refId=s7V7mSX5gk4u6asyU2%2Bizg%3D%3D&trackingId=v0luJHdqRK1OWdC7JiBzsA%3D%3D",
      "listing_id": "urn:li:jobPosting:4167558532"
    },
    {
      "title": "Project Associate - Parliament",
      "company": "UNDP in the Arab States region",
      "location": "Colombo, Western Province, Sri Lanka",
      "posted_date": "2 weeks ago",
      "job_url": "https://lk.linkedin.com/jobs/view/project-associate-parliament-at-undp-in-the-arab-states-region-4183014563?position=19&pageNum=0&refId=s7V7mSX5gk4u6asyU2%2Bizg%3D%3D&trackingId=5SUQD3xWoOYuajzGibA9%2Bg%3D%3D",
      "listing_id": "urn:li:jobPosting:4183014563"
    },
    {
      "title": "Country Manager",
      "company": "Smart Quest Consultancy",
      "location": "Colombo, Western Province, Sri Lanka",
      "posted_date": "1 week ago",
      "job_url": "https://lk.linkedin.com/jobs/view/country-manager-at-smart-quest-consultancy-4187306173?position=20&pageNum=0&refId=s7V7mSX5gk4u6asyU2%2Bizg%3D%3D&trackingId=6xZVTg%2F2TJpzP%2F71uYYLdg%3D%3D",
      "listing_id": "urn:li:jobPosting:4187306173"
    },
    {
      "title": "Accountant (Remote)",
      "company": "ArchipelagoHR",
      "location": "Sri Lanka",
      "posted_date": "4 days ago",
      "job_url": "https://lk.linkedin.com/jobs/view/accountant-remote-at-archipelagohr-4193822341?position=21&pageNum=0&refId=s7V7mSX5gk4u6asyU2%2Bizg%3D%3D&trackingId=i1M47O5qBiXhVx0Y0Mv64A%3D%3D",
      "listing_id": "urn:li:jobPosting:4193822341"
    },
    {
      "title": "Area Sales Manager",
      "company": "Perfetti Van Melle",
      "location": "Rajagiriya, Western Province, Sri Lanka",
      "posted_date": "1 week ago",
      "job_url": "https://lk.linkedin.com/jobs/view/area-sales-manager-at-perfetti-van-melle-4185497071?position=22&pageNum=0&refId=s7V7mSX5gk4u6asyU2%2Bizg%3D%3D&trackingId=oYl511Uv9o4fjCnoJUAuQQ%3D%3D",
      "listing_id": "urn:li:jobPosting:4185497071"
    },
    {
      "title": "Frontend Developer",
      "company": "qlub",
      "location": "Colombo, Western Province, Sri Lanka",
      "posted_date": "1 week ago",
      "job_url": "https://lk.linkedin.com/jobs/view/frontend-developer-at-qlub-4190294613?position=23&pageNum=0&refId=s7V7mSX5gk4u6asyU2%2Bizg%3D%3D&trackingId=Yd0EDu4ClDT%2BfbGpuInxvg%3D%3D",
      "listing_id": "urn:li:jobPosting:4190294613"
    },
    {
      "title": "Assistant Accountant - Borelasgamuwa",
      "company": "Smart Quest Consultancy",
      "location": "Boralesgamuwa, Western Province, Sri Lanka",
      "posted_date": "1 month ago",
      "job_url": "https://lk.linkedin.com/jobs/view/assistant-accountant-borelasgamuwa-at-smart-quest-consultancy-4159772070?position=24&pageNum=0&refId=s7V7mSX5gk4u6asyU2%2Bizg%3D%3D&trackingId=d7JfeBn2C79aXY2e1cK2Sg%3D%3D",
      "listing_id": "urn:li:jobPosting:4159772070"
    },
    {
      "title": "Administrative Assistant",
      "company": "AirCheck India Private Limited",
      "location": "Sri Lanka",
      "posted_date": "1 month ago",
      "job_url": "https://lk.linkedin.com/jobs/view/administrative-assistant-at-aircheck-india-private-limited-4141455365?position=25&pageNum=0&refId=s7V7mSX5gk4u6asyU2%2Bizg%3D%3D&trackingId=VhDJuZ2OPmKUaFSTR6vAkA%3D%3D",
      "listing_id": "urn:li:jobPosting:4141455365"
    },
    {
      "title": "Associate - HR Operations",
      "company": "Axiata Digital Labs",
      "location": "Colombo, Western Province, Sri Lanka",
      "posted_date": "1 week ago",
      "job_url": "https://lk.linkedin.com/jobs/view/associate-hr-operations-at-axiata-digital-labs-4185738281?position=26&pageNum=0&refId=s7V7mSX5gk4u6asyU2%2Bizg%3D%3D&trackingId=1S9EYkUvRrZd1%2FIEoIoFCw%3D%3D",
      "listing_id": "urn:li:jobPosting:4185738281"
    },
    {
      "title": "HR Executive -0024",
      "company": "NativeWay",
      "location": "Colombo, Western Province, Sri Lanka",
      "posted_date": "3 weeks ago",
      "job_url": "https://lk.linkedin.com/jobs/view/hr-executive-0024-at-nativeway-4180907431?position=27&pageNum=0&refId=s7V7mSX5gk4u6asyU2%2Bizg%3D%3D&trackingId=KW1pmLqcBMsKpI7hg8Fs8w%3D%3D",
      "listing_id": "urn:li:jobPosting:4180907431"
    },
    {
      "title": "Procurement and Contracts Coordinator",
      "company": "Otago Regional Council",
      "location": "Badulla District, Uva Province, Sri Lanka",
      "posted_date": "1 week ago",
      "job_url": "https://lk.linkedin.com/jobs/view/procurement-and-contracts-coordinator-at-otago-regional-council-4190291289?position=28&pageNum=0&refId=s7V7mSX5gk4u6asyU2%2Bizg%3D%3D&trackingId=jZ3MyKi3tCSZg4cCbzqUiQ%3D%3D",
      "listing_id": "urn:li:jobPosting:4190291289"
    },
    {
      "title": "Assistant Brand Manager",
      "company": "Fonterra",
      "location": "Biyagama, Western Province, Sri Lanka",
      "posted_date": "2 weeks ago",
      "job_url": "https://lk.linkedin.com/jobs/view/assistant-brand-manager-at-fonterra-4182113544?position=29&pageNum=0&refId=s7V7mSX5gk4u6asyU2%2Bizg%3D%3D&trackingId=xxWAEmHYj%2Bzz5au7cnpUiA%3D%3D",
      "listing_id": "urn:li:jobPosting:4182113544"
    },
    {
      "title": "Quantity Surveyor - Civil (Water) - 0027",
      "company": "NativeWay",
      "location": "Colombo, Western Province, Sri Lanka",
      "posted_date": "4 days ago",
      "job_url": "https://lk.linkedin.com/jobs/view/quantity-surveyor-civil-water-0027-at-nativeway-4194278861?position=30&pageNum=0&refId=s7V7mSX5gk4u6asyU2%2Bizg%3D%3D&trackingId=8KwM%2FUBm52A279w%2BSax41w%3D%3D",
      "listing_id": "urn:li:jobPosting:4194278861"
    },
    {
      "title": "HR Executive",
      "company": "Smart Quest Consultancy",
      "location": "Colombo, Western Province, Sri Lanka",
      "posted_date": "5 days ago",
      "job_url": "https://lk.linkedin.com/jobs/view/hr-executive-at-smart-quest-consultancy-4189711071?position=31&pageNum=0&refId=s7V7mSX5gk4u6asyU2%2Bizg%3D%3D&trackingId=1FiRUABRmTfMss%2Bk0SKkmQ%3D%3D",
      "listing_id": "urn:li:jobPosting:4189711071"
    },
    {
      "title": "Technical Support Officer",
      "company": "Prime One Global",
      "location": "Colombo, Western Province, Sri Lanka",
      "posted_date": "4 days ago",
      "job_url": "https://lk.linkedin.com/jobs/view/technical-support-officer-at-prime-one-global-4191108365?position=32&pageNum=0&refId=s7V7mSX5gk4u6asyU2%2Bizg%3D%3D&trackingId=vNPwuzJUw81VSKw566Ppdw%3D%3D",
      "listing_id": "urn:li:jobPosting:4191108365"
    },
    {
      "title": "Accountant - FMCG",
      "company": "Smart Quest Consultancy",
      "location": "Kuliyapitiya, North Western Province, Sri Lanka",
      "posted_date": "5 days ago",
      "job_url": "https://lk.linkedin.com/jobs/view/accountant-fmcg-at-smart-quest-consultancy-4189709161?position=33&pageNum=0&refId=s7V7mSX5gk4u6asyU2%2Bizg%3D%3D&trackingId=rrXfG9VY6fQtZzDu4JFDOg%3D%3D",
      "listing_id": "urn:li:jobPosting:4189709161"
    },
    {
      "title": "Desktop Engineer Level 2",
      "company": "Dijital Team",
      "location": "Colombo, Western Province, Sri Lanka",
      "posted_date": "5 days ago",
      "job_url": "https://lk.linkedin.com/jobs/view/desktop-engineer-level-2-at-dijital-team-4188565581?position=34&pageNum=0&refId=s7V7mSX5gk4u6asyU2%2Bizg%3D%3D&trackingId=zNkna6RATqz2atOpRgFxXA%3D%3D",
      "listing_id": "urn:li:jobPosting:4188565581"
    },
    {
      "title": "Tour Executive",
      "company": "Trip Fusion DMC",
      "location": "Colombo, Western Province, Sri Lanka",
      "posted_date": "1 week ago",
      "job_url": "https://lk.linkedin.com/jobs/view/tour-executive-at-trip-fusion-dmc-4184113841?position=35&pageNum=0&refId=s7V7mSX5gk4u6asyU2%2Bizg%3D%3D&trackingId=bnYLytguYOvKPZufw%2F54DQ%3D%3D",
      "listing_id": "urn:li:jobPosting:4184113841"
    },
    {
      "title": "Freelance Country Expert (Pakistan)",
      "company": "Lion Group",
      "location": "Sri Lanka",
      "posted_date": "4 days ago",
      "job_url": "https://lk.linkedin.com/jobs/view/freelance-country-expert-pakistan-at-lion-group-4193624134?position=36&pageNum=0&refId=s7V7mSX5gk4u6asyU2%2Bizg%3D%3D&trackingId=u4FciJIFEGGT5SRZMhLh%2Bw%3D%3D",
      "listing_id": "urn:li:jobPosting:4193624134"
    },
    {
      "title": "Business Development Manager",
      "company": "Asia Petrochemicals",
      "location": "Sri Lanka",
      "posted_date": "5 months ago",
      "job_url": "https://lk.linkedin.com/jobs/view/business-development-manager-at-asia-petrochemicals-4055734624?position=37&pageNum=0&refId=s7V7mSX5gk4u6asyU2%2Bizg%3D%3D&trackingId=tXVkMJrf6twKLHDj%2Bun4bw%3D%3D",
      "listing_id": "urn:li:jobPosting:4055734624"
    },
    {
      "title": "Junior Accountant",
      "company": "Prime One Global",
      "location": "Colombo, Western Province, Sri Lanka",
      "posted_date": "4 days ago",
      "job_url": "https://lk.linkedin.com/jobs/view/junior-accountant-at-prime-one-global-4191107476?position=38&pageNum=0&refId=s7V7mSX5gk4u6asyU2%2Bizg%3D%3D&trackingId=%2BsjZkZSua%2Fz5TDFbwht1%2FA%3D%3D",
      "listing_id": "urn:li:jobPosting:4191107476"
    },
    {
      "title": "Executive - Finance",
      "company": "Altrium",
      "location": "Colombo, Western Province, Sri Lanka",
      "posted_date": "2 months ago",
      "job_url": "https://lk.linkedin.com/jobs/view/executive-finance-at-altrium-4127242785?position=39&pageNum=0&refId=s7V7mSX5gk4u6asyU2%2Bizg%3D%3D&trackingId=YXylEW8Z4tGB3HCqwiZKiQ%3D%3D",
      "listing_id": "urn:li:jobPosting:4127242785"
    },
    {
      "title": "Associate Technical Engineer",
      "company": "Embla Software Innovation (pvt) Ltd",
      "location": "Colombo, Western Province, Sri Lanka",
      "posted_date": "",
      "job_url": "https://lk.linkedin.com/jobs/view/associate-technical-engineer-at-embla-software-innovation-pvt-ltd-4192598789?position=40&pageNum=0&refId=s7V7mSX5gk4u6asyU2%2Bizg%3D%3D&trackingId=dZw8ZS0QFrHo%2BHljdhzI0A%3D%3D",
      "listing_id": "urn:li:jobPosting:4192598789"
    },
    {
      "title": "Multimedia Designer",
      "company": "AuroraRCM",
      "location": "Colombo, Western Province, Sri Lanka",
      "posted_date": "1 month ago",
      "job_url": "https://lk.linkedin.com/jobs/view/multimedia-designer-at-aurorarcm-4142600630?position=41&pageNum=0&refId=s7V7mSX5gk4u6asyU2%2Bizg%3D%3D&trackingId=idtm6h4W%2FeGktwrLRvWUvQ%3D%3D",
      "listing_id": "urn:li:jobPosting:4142600630"
    },
    {
      "title": "Music Copyright Associate - YouTube Claiming",
      "company": "Orfium",
      "location": "Colombo, Western Province, Sri Lanka",
      "posted_date": "3 weeks ago",
      "job_url": "https://lk.linkedin.com/jobs/view/music-copyright-associate-youtube-claiming-at-orfium-4195523944?position=42&pageNum=0&refId=s7V7mSX5gk4u6asyU2%2Bizg%3D%3D&trackingId=Bkoj0a9y6u5znCf0igi7pw%3D%3D",
      "listing_id": "urn:li:jobPosting:4195523944"
    },
    {
      "title": "Assistant Manager - Supply Chain & Administration",
      "company": "Cenmetrix",
      "location": "Colombo, Western Province, Sri Lanka",
      "posted_date": "5 days ago",
      "job_url": "https://lk.linkedin.com/jobs/view/assistant-manager-supply-chain-administration-at-cenmetrix-4192883580?position=43&pageNum=0&refId=s7V7mSX5gk4u6asyU2%2Bizg%3D%3D&trackingId=6%2FF12cV0lI%2FOkQbm9m8%2FIA%3D%3D",
      "listing_id": "urn:li:jobPosting:4192883580"
    },
    {
      "title": "Trainee Analyst / Analyst / Senior Analyst",
      "company": "EY",
      "location": "Colombo, Western Province, Sri Lanka",
      "posted_date": "2 days ago",
      "job_url": "https://lk.linkedin.com/jobs/view/trainee-analyst-analyst-senior-analyst-at-ey-4193080308?position=44&pageNum=0&refId=s7V7mSX5gk4u6asyU2%2Bizg%3D%3D&trackingId=7EZzoDKiwCQQ5jmf0JGjZQ%3D%3D",
      "listing_id": "urn:li:jobPosting:4193080308"
    },
    {
      "title": "Web Developer - AU Hours",
      "company": "Hype Invention",
      "location": "Colombo, Western Province, Sri Lanka",
      "posted_date": "1 week ago",
      "job_url": "https://lk.linkedin.com/jobs/view/web-developer-au-hours-at-hype-invention-4185265155?position=45&pageNum=0&refId=s7V7mSX5gk4u6asyU2%2Bizg%3D%3D&trackingId=Z%2BbPsqjEpu2G3p4oEMQ1pA%3D%3D",
      "listing_id": "urn:li:jobPosting:4185265155"
    },
    {
      "title": "Software Engineer - Frontend",
      "company": "Code94 Labs",
      "location": "Colombo, Western Province, Sri Lanka",
      "posted_date": "3 months ago",
      "job_url": "https://lk.linkedin.com/jobs/view/software-engineer-frontend-at-code94-labs-4104128277?position=46&pageNum=0&refId=s7V7mSX5gk4u6asyU2%2Bizg%3D%3D&trackingId=ke5bBogLnO4gXG6t6k40Nw%3D%3D",
      "listing_id": "urn:li:jobPosting:4104128277"
    },
    {
      "title": "Researcher - Data Science (Globally Recruited)",
      "company": "International Water Management Institute (IWMI)",
      "location": "Colombo, Western Province, Sri Lanka",
      "posted_date": "3 weeks ago",
      "job_url": "https://lk.linkedin.com/jobs/view/researcher-data-science-globally-recruited-at-international-water-management-institute-iwmi-4174598581?position=47&pageNum=0&refId=s7V7mSX5gk4u6asyU2%2Bizg%3D%3D&trackingId=3p065QRHLSEMKmUWSlCGhg%3D%3D",
      "listing_id": "urn:li:jobPosting:4174598581"
    },
    {
      "title": "Security Analyst",
      "company": "blueAPACHE",
      "location": "Sri Lanka",
      "posted_date": "1 month ago",
      "job_url": "https://lk.linkedin.com/jobs/view/security-analyst-at-blueapache-4169182603?position=48&pageNum=0&refId=s7V7mSX5gk4u6asyU2%2Bizg%3D%3D&trackingId=8BjeTEXnY%2BT%2F5bZj8zVbzQ%3D%3D",
      "listing_id": "urn:li:jobPosting:4169182603"
    },
    {
      "title": "Creative Designer",
      "company": "Code94 Labs",
      "location": "Colombo, Western Province, Sri Lanka",
      "posted_date": "3 months ago",
      "job_url": "https://lk.linkedin.com/jobs/view/creative-designer-at-code94-labs-4104128287?position=49&pageNum=0&refId=s7V7mSX5gk4u6asyU2%2Bizg%3D%3D&trackingId=zh8mQSBAldmJ5shNFSY%2BsA%3D%3D",
      "listing_id": "urn:li:jobPosting:4104128287"
    },
    {
      "title": "Account Assistant / Co-ordinator",
      "company": "Edith Cowan University - Sri Lanka",
      "location": "Sri Jayawardenepura Kotte, Western Province, Sri Lanka",
      "posted_date": "1 week ago",
      "job_url": "https://lk.linkedin.com/jobs/view/account-assistant-co-ordinator-at-edith-cowan-university-sri-lanka-4189267509?position=50&pageNum=0&refId=s7V7mSX5gk4u6asyU2%2Bizg%3D%3D&trackingId=bXgkKXCEw8r21foRanm9UA%3D%3D",
      "listing_id": "urn:li:jobPosting:4189267509"
    },
    {
      "title": "Country Head",
      "company": "CAREER141",
      "location": "Colombo District, Western Province, Sri Lanka",
      "posted_date": "1 week ago",
      "job_url": "https://lk.linkedin.com/jobs/view/country-head-at-career141-4189264313?position=51&pageNum=0&refId=s7V7mSX5gk4u6asyU2%2Bizg%3D%3D&trackingId=t5SICFnY8hcj3tizlKEx1g%3D%3D",
      "listing_id": "urn:li:jobPosting:4189264313"
    },
    {
      "title": "Procurement Analyst",
      "company": "IFS assyst",
      "location": "Colombo, Western Province, Sri Lanka",
      "posted_date": "4 months ago",
      "job_url": "https://lk.linkedin.com/jobs/view/procurement-analyst-at-ifs-assyst-4095097972?position=52&pageNum=0&refId=s7V7mSX5gk4u6asyU2%2Bizg%3D%3D&trackingId=Ndst4uQUozx9UYBERtBoiw%3D%3D",
      "listing_id": "urn:li:jobPosting:4095097972"
    },
    {
      "title": "IT-Administrator (m/f/d)",
      "company": "KRAMSKI Lanka (Pvt) Ltd.",
      "location": "Katunayake, Western Province, Sri Lanka",
      "posted_date": "2 days ago",
      "job_url": "https://lk.linkedin.com/jobs/view/it-administrator-m-f-d-at-kramski-lanka-pvt-ltd-4193408668?position=53&pageNum=0&refId=s7V7mSX5gk4u6asyU2%2Bizg%3D%3D&trackingId=itgwjQlUIOMlTT%2BdapHWkQ%3D%3D",
      "listing_id": "urn:li:jobPosting:4193408668"
    },
    {
      "title": "Program Manager",
      "company": "Fortude",
      "location": "Colombo, Western Province, Sri Lanka",
      "posted_date": "2 weeks ago",
      "job_url": "https://lk.linkedin.com/jobs/view/program-manager-at-fortude-4182580868?position=54&pageNum=0&refId=s7V7mSX5gk4u6asyU2%2Bizg%3D%3D&trackingId=37QLVpS4phmzrRQberKcqA%3D%3D",
      "listing_id": "urn:li:jobPosting:4182580868"
    },
    {
      "title": "Showroom Manager",
      "company": "Touch of Gold Lanka (Private) Limited",
      "location": "Colombo, Western Province, Sri Lanka",
      "posted_date": "3 days ago",
      "job_url": "https://lk.linkedin.com/jobs/view/showroom-manager-at-touch-of-gold-lanka-private-limited-4193827332?position=55&pageNum=0&refId=s7V7mSX5gk4u6asyU2%2Bizg%3D%3D&trackingId=zHXRZ8QZXA80c%2Faf7BnL%2BQ%3D%3D",
      "listing_id": "urn:li:jobPosting:4193827332"
    },
    {
      "title": "Marketing Associate - VET (Remote)",
      "company": "EKWA MARKETING.",
      "location": "Sri Lanka",
      "posted_date": "1 month ago",
      "job_url": "https://lk.linkedin.com/jobs/view/marketing-associate-vet-remote-at-ekwa-marketing-4157710587?position=56&pageNum=0&refId=s7V7mSX5gk4u6asyU2%2Bizg%3D%3D&trackingId=ZS43KbCQMuRqZ7TtawAApw%3D%3D",
      "listing_id": "urn:li:jobPosting:4157710587"
    },
    {
      "title": "Music Copyright Associate - Youtube Claiming Team (Talent Pipeline Building)",
      "company": "Orfium",
      "location": "Colombo, Western Province, Sri Lanka",
      "posted_date": "1 month ago",
      "job_url": "https://lk.linkedin.com/jobs/view/music-copyright-associate-youtube-claiming-team-talent-pipeline-building-at-orfium-4191082533?position=57&pageNum=0&refId=s7V7mSX5gk4u6asyU2%2Bizg%3D%3D&trackingId=qRYxwngwlGB9i2X%2BNnRgFw%3D%3D",
      "listing_id": "urn:li:jobPosting:4191082533"
    },
    {
      "title": "Data Processing & Analyzing Associate (Talent Pipeline Building)",
      "company": "Orfium",
      "location": "Colombo, Western Province, Sri Lanka",
      "posted_date": "8 months ago",
      "job_url": "https://lk.linkedin.com/jobs/view/data-processing-analyzing-associate-talent-pipeline-building-at-orfium-3997097048?position=58&pageNum=0&refId=s7V7mSX5gk4u6asyU2%2Bizg%3D%3D&trackingId=Vg3mnPE97uV49OY6IxTjrA%3D%3D",
      "listing_id": "urn:li:jobPosting:3997097048"
    },
    {
      "title": "Kitchen Staff",
      "company": "Opaa! Food Management",
      "location": "Galle, Southern Province, Sri Lanka",
      "posted_date": "3 weeks ago",
      "job_url": "https://lk.linkedin.com/jobs/view/kitchen-staff-at-opaa%21-food-management-4178073834?position=59&pageNum=0&refId=s7V7mSX5gk4u6asyU2%2Bizg%3D%3D&trackingId=HgiI5ddwdBswmmxaTkq0Jg%3D%3D",
      "listing_id": "urn:li:jobPosting:4178073834"
    },
    {
      "title": "Product Manager",
      "company": "Altrium",
      "location": "Colombo, Western Province, Sri Lanka",
      "posted_date": "1 month ago",
      "job_url": "https://lk.linkedin.com/jobs/view/product-manager-at-altrium-4159648408?position=60&pageNum=0&refId=s7V7mSX5gk4u6asyU2%2Bizg%3D%3D&trackingId=2JL1LlSjXYzy%2BI8spXEP9g%3D%3D",
      "listing_id": "urn:li:jobPosting:4159648408"
    },
    {
      "title": "Associate - HR Operations",
      "company": "Axiata Digital Labs",
      "location": "Colombo, Western Province, Sri Lanka",
      "posted_date": "1 week ago",
      "job_url": "https://lk.linkedin.com/jobs/view/associate-hr-operations-at-axiata-digital-labs-4185738281?position=1&pageNum=2&refId=Fei0OAn8P1E2g6KOvniaxQ%3D%3D&trackingId=8F3NqviVqi6sTJDmfDT7yA%3D%3D",
      "listing_id": "urn:li:jobPosting:4185738281"
    },
    {
      "title": "HR Executive -0024",
      "company": "NativeWay",
      "location": "Colombo, Western Province, Sri Lanka",
      "posted_date": "3 weeks ago",
      "job_url": "https://lk.linkedin.com/jobs/view/hr-executive-0024-at-nativeway-4180907431?position=2&pageNum=2&refId=Fei0OAn8P1E2g6KOvniaxQ%3D%3D&trackingId=5lFHn4nPfQnO9sYCyJrB3g%3D%3D",
      "listing_id": "urn:li:jobPosting:4180907431"
    },
    {
      "title": "Procurement and Contracts Coordinator",
      "company": "Otago Regional Council",
      "location": "Badulla District, Uva Province, Sri Lanka",
      "posted_date": "1 week ago",
      "job_url": "https://lk.linkedin.com/jobs/view/procurement-and-contracts-coordinator-at-otago-regional-council-4190291289?position=3&pageNum=2&refId=Fei0OAn8P1E2g6KOvniaxQ%3D%3D&trackingId=VhgVmASjslccWI%2B1zICPSw%3D%3D",
      "listing_id": "urn:li:jobPosting:4190291289"
    },
    {
      "title": "Assistant Brand Manager",
      "company": "Fonterra",
      "location": "Biyagama, Western Province, Sri Lanka",
      "posted_date": "2 weeks ago",
      "job_url": "https://lk.linkedin.com/jobs/view/assistant-brand-manager-at-fonterra-4182113544?position=4&pageNum=2&refId=Fei0OAn8P1E2g6KOvniaxQ%3D%3D&trackingId=jB6INadIt8yJO%2BPbOm5F7g%3D%3D",
      "listing_id": "urn:li:jobPosting:4182113544"
    },
    {
      "title": "Quantity Surveyor - Civil (Water) - 0027",
      "company": "NativeWay",
      "location": "Colombo, Western Province, Sri Lanka",
      "posted_date": "4 days ago",
      "job_url": "https://lk.linkedin.com/jobs/view/quantity-surveyor-civil-water-0027-at-nativeway-4194278861?position=5&pageNum=2&refId=Fei0OAn8P1E2g6KOvniaxQ%3D%3D&trackingId=AlFxq0qweWzqB9JBskzbkg%3D%3D",
      "listing_id": "urn:li:jobPosting:4194278861"
    },
    {
      "title": "Technical Support Officer",
      "company": "Prime One Global",
      "location": "Colombo, Western Province, Sri Lanka",
      "posted_date": "4 days ago",
      "job_url": "https://lk.linkedin.com/jobs/view/technical-support-officer-at-prime-one-global-4191108365?position=6&pageNum=2&refId=Fei0OAn8P1E2g6KOvniaxQ%3D%3D&trackingId=uSoSk8HwWr0t4do1JwmOqQ%3D%3D",
      "listing_id": "urn:li:jobPosting:4191108365"
    },
    {
      "title": "HR Executive",
      "company": "Smart Quest Consultancy",
      "location": "Colombo, Western Province, Sri Lanka",
      "posted_date": "5 days ago",
      "job_url": "https://lk.linkedin.com/jobs/view/hr-executive-at-smart-quest-consultancy-4189711071?position=7&pageNum=2&refId=Fei0OAn8P1E2g6KOvniaxQ%3D%3D&trackingId=Ued40eSdtGr%2F%2BZOb4WLHoA%3D%3D",
      "listing_id": "urn:li:jobPosting:4189711071"
    },
    {
      "title": "Accountant - FMCG",
      "company": "Smart Quest Consultancy",
      "location": "Kuliyapitiya, North Western Province, Sri Lanka",
      "posted_date": "5 days ago",
      "job_url": "https://lk.linkedin.com/jobs/view/accountant-fmcg-at-smart-quest-consultancy-4189709161?position=8&pageNum=2&refId=Fei0OAn8P1E2g6KOvniaxQ%3D%3D&trackingId=DLsyfsolLn%2FIhmE8Gm4pIQ%3D%3D",
      "listing_id": "urn:li:jobPosting:4189709161"
    },
    {
      "title": "Desktop Engineer Level 2",
      "company": "Dijital Team",
      "location": "Colombo, Western Province, Sri Lanka",
      "posted_date": "5 days ago",
      "job_url": "https://lk.linkedin.com/jobs/view/desktop-engineer-level-2-at-dijital-team-4188565581?position=9&pageNum=2&refId=Fei0OAn8P1E2g6KOvniaxQ%3D%3D&trackingId=%2FMHjiB5%2FP4XquIOIlBW%2BuA%3D%3D",
      "listing_id": "urn:li:jobPosting:4188565581"
    },
    {
      "title": "Tour Executive",
      "company": "Trip Fusion DMC",
      "location": "Colombo, Western Province, Sri Lanka",
      "posted_date": "1 week ago",
      "job_url": "https://lk.linkedin.com/jobs/view/tour-executive-at-trip-fusion-dmc-4184113841?position=10&pageNum=2&refId=Fei0OAn8P1E2g6KOvniaxQ%3D%3D&trackingId=pbJMJcCcf4avoe0AtFyUsg%3D%3D",
      "listing_id": "urn:li:jobPosting:4184113841"
    },
    {
      "title": "Project Manager",
      "company": "Code94 Labs",
      "location": "Colombo, Western Province, Sri Lanka",
      "posted_date": "3 months ago",
      "job_url": "https://lk.linkedin.com/jobs/view/project-manager-at-code94-labs-4104126304?position=1&pageNum=7&refId=OjyyQ%2BpNsregI50JzvZSDQ%3D%3D&trackingId=Pud2tRMtV7H71mzSHrHHPw%3D%3D",
      "listing_id": "urn:li:jobPosting:4104126304"
    },
    {
      "title": "Reservations Manager",
      "company": "FIGO HOLIDAYS (PVT) LTD.",
      "location": "Colombo, Western Province, Sri Lanka",
      "posted_date": "1 week ago",
      "job_url": "https://lk.linkedin.com/jobs/view/reservations-manager-at-figo-holidays-pvt-ltd-4185409189?position=2&pageNum=7&refId=OjyyQ%2BpNsregI50JzvZSDQ%3D%3D&trackingId=TJg3IqSO3RT36lKHn8T4pA%3D%3D",
      "listing_id": "urn:li:jobPosting:4185409189"
    },
    {
      "title": "Finance & Admin Executive",
      "company": "DoMedia",
      "location": "Colombo, Western Province, Sri Lanka",
      "posted_date": "1 month ago",
      "job_url": "https://lk.linkedin.com/jobs/view/finance-admin-executive-at-domedia-4150913281?position=3&pageNum=7&refId=OjyyQ%2BpNsregI50JzvZSDQ%3D%3D&trackingId=9kZOqxgdFQ14gaIY9D2s5g%3D%3D",
      "listing_id": "urn:li:jobPosting:4150913281"
    },
    {
      "title": "Freelance Country Expert (India)",
      "company": "Lion Group",
      "location": "Sri Lanka",
      "posted_date": "4 days ago",
      "job_url": "https://lk.linkedin.com/jobs/view/freelance-country-expert-india-at-lion-group-4193617875?position=4&pageNum=7&refId=OjyyQ%2BpNsregI50JzvZSDQ%3D%3D&trackingId=YC%2BqhPQRUm2%2BtHy0jfkpIw%3D%3D",
      "listing_id": "urn:li:jobPosting:4193617875"
    },
    {
      "title": "React Developer",
      "company": "iLabs",
      "location": "Battaramulla, Western Province, Sri Lanka",
      "posted_date": "6 days ago",
      "job_url": "https://lk.linkedin.com/jobs/view/react-developer-at-ilabs-4192057588?position=5&pageNum=7&refId=OjyyQ%2BpNsregI50JzvZSDQ%3D%3D&trackingId=geFilcqt1mAdfBnhm76nDA%3D%3D",
      "listing_id": "urn:li:jobPosting:4192057588"
    },
    {
      "title": "Business Analyst",
      "company": "OrangeHRM",
      "location": "Colombo, Western Province, Sri Lanka",
      "posted_date": "1 month ago",
      "job_url": "https://lk.linkedin.com/jobs/view/business-analyst-at-orangehrm-4142324251?position=6&pageNum=7&refId=OjyyQ%2BpNsregI50JzvZSDQ%3D%3D&trackingId=OxSZ1kZ4J%2B50EymXUu%2FPuA%3D%3D",
      "listing_id": "urn:li:jobPosting:4142324251"
    },
    {
      "title": "Intern - Frontend",
      "company": "Octopus BI",
      "location": "Colombo, Western Province, Sri Lanka",
      "posted_date": "2 months ago",
      "job_url": "https://lk.linkedin.com/jobs/view/intern-frontend-at-octopus-bi-4138067063?position=7&pageNum=7&refId=OjyyQ%2BpNsregI50JzvZSDQ%3D%3D&trackingId=eEmktD%2B4g0sIDo6sLMvzVw%3D%3D",
      "listing_id": "urn:li:jobPosting:4138067063"
    },
    {
      "title": "Assistant General Manager / General Manager - RCM Operations",
      "company": "AuroraRCM",
      "location": "Colombo, Western Province, Sri Lanka",
      "posted_date": "2 weeks ago",
      "job_url": "https://lk.linkedin.com/jobs/view/assistant-general-manager-general-manager-rcm-operations-at-aurorarcm-4186188668?position=8&pageNum=7&refId=OjyyQ%2BpNsregI50JzvZSDQ%3D%3D&trackingId=VySQp7nyaxkH%2BIi3sp2hBg%3D%3D",
      "listing_id": "urn:li:jobPosting:4186188668"
    },
    {
      "title": "Channel Sales Manager",
      "company": "OREL IT",
      "location": "Colombo, Western Province, Sri Lanka",
      "posted_date": "2 days ago",
      "job_url": "https://lk.linkedin.com/jobs/view/channel-sales-manager-at-orel-it-4191887916?position=9&pageNum=7&refId=OjyyQ%2BpNsregI50JzvZSDQ%3D%3D&trackingId=lLe6jiFS6394YtVNlBfwhQ%3D%3D",
      "listing_id": "urn:li:jobPosting:4191887916"
    },
    {
      "title": "Digital Marketing Executive",
      "company": "DoMedia",
      "location": "Colombo, Western Province, Sri Lanka",
      "posted_date": "2 months ago",
      "job_url": "https://lk.linkedin.com/jobs/view/digital-marketing-executive-at-domedia-4127922005?position=10&pageNum=7&refId=OjyyQ%2BpNsregI50JzvZSDQ%3D%3D&trackingId=uP3JQT2tEeZuAZAIcpmZQQ%3D%3D",
      "listing_id": "urn:li:jobPosting:4127922005"
    },
    {
      "title": "Behavioral Health Coach (Sri Lanka)",
      "company": "Intellect",
      "location": "Sri Lanka",
      "posted_date": "1 year ago",
      "job_url": "https://lk.linkedin.com/jobs/view/behavioral-health-coach-sri-lanka-at-intellect-3891666906?position=1&pageNum=10&refId=RmfV2i6KVltbgMmh3pQ7OQ%3D%3D&trackingId=TOLar6v6LK5aZmAhoB5kGQ%3D%3D",
      "listing_id": "urn:li:jobPosting:3891666906"
    },
    {
      "title": "Full Stack Developer",
      "company": "Fintechnology Asia Pacific (FINAP)",
      "location": "Colombo, Western Province, Sri Lanka",
      "posted_date": "1 month ago",
      "job_url": "https://lk.linkedin.com/jobs/view/full-stack-developer-at-fintechnology-asia-pacific-finap-4167305120?position=2&pageNum=10&refId=RmfV2i6KVltbgMmh3pQ7OQ%3D%3D&trackingId=V9HV5PqHI%2FgG5hQ9YnFlig%3D%3D",
      "listing_id": "urn:li:jobPosting:4167305120"
    },
    {
      "title": "Business Development Manager - Corporate",
      "company": "Shangri-La Group",
      "location": "Colombo, Western Province, Sri Lanka",
      "posted_date": "1 week ago",
      "job_url": "https://lk.linkedin.com/jobs/view/business-development-manager-corporate-at-shangri-la-group-4185702428?position=3&pageNum=10&refId=RmfV2i6KVltbgMmh3pQ7OQ%3D%3D&trackingId=KmZSY5zNrpNwhvosDi8S%2BA%3D%3D",
      "listing_id": "urn:li:jobPosting:4185702428"
    },
    {
      "title": "Accounts Receivable Executive",
      "company": "IFS",
      "location": "Colombo, Western Province, Sri Lanka",
      "posted_date": "1 week ago",
      "job_url": "https://lk.linkedin.com/jobs/view/accounts-receivable-executive-at-ifs-4191720175?position=4&pageNum=10&refId=RmfV2i6KVltbgMmh3pQ7OQ%3D%3D&trackingId=WjToRZ2dTUlkoYcEsiItvQ%3D%3D",
      "listing_id": "urn:li:jobPosting:4191720175"
    },
    {
      "title": "Business Analyst – Intern",
      "company": "DoMedia",
      "location": "Colombo, Western Province, Sri Lanka",
      "posted_date": "2 months ago",
      "job_url": "https://lk.linkedin.com/jobs/view/business-analyst-%E2%80%93-intern-at-domedia-4127918638?position=5&pageNum=10&refId=RmfV2i6KVltbgMmh3pQ7OQ%3D%3D&trackingId=sQCWm1dFSCOt9eR0aXnwFw%3D%3D",
      "listing_id": "urn:li:jobPosting:4127918638"
    },
    {
      "title": "Assistant Manager Production",
      "company": "Smart Quest Consultancy",
      "location": "Kuliyapitiya, North Western Province, Sri Lanka",
      "posted_date": "1 week ago",
      "job_url": "https://lk.linkedin.com/jobs/view/assistant-manager-production-at-smart-quest-consultancy-4185735532?position=6&pageNum=10&refId=RmfV2i6KVltbgMmh3pQ7OQ%3D%3D&trackingId=5XGLmCSBJMYTiWmSxVqnrw%3D%3D",
      "listing_id": "urn:li:jobPosting:4185735532"
    },
    {
      "title": "Junior Executive Human Resources",
      "company": "Lathpandura Holdings Pvt. Ltd.",
      "location": "Polonnaruwa, North Central Province, Sri Lanka",
      "posted_date": "1 week ago",
      "job_url": "https://lk.linkedin.com/jobs/view/junior-executive-human-resources-at-lathpandura-holdings-pvt-ltd-4185444019?position=7&pageNum=10&refId=RmfV2i6KVltbgMmh3pQ7OQ%3D%3D&trackingId=vAOGF5OUMqJzpxY2fl0Esw%3D%3D",
      "listing_id": "urn:li:jobPosting:4185444019"
    },
    {
      "title": "Landscape Architect",
      "company": "CID",
      "location": "Sri Lanka",
      "posted_date": "3 weeks ago",
      "job_url": "https://lk.linkedin.com/jobs/view/landscape-architect-at-cid-4172593138?position=8&pageNum=10&refId=RmfV2i6KVltbgMmh3pQ7OQ%3D%3D&trackingId=eBP0MEFDYjyX%2BthfTQif0Q%3D%3D",
      "listing_id": "urn:li:jobPosting:4172593138"
    },
    {
      "title": "Sinhala VRI/OPI Interpretation Vacancy - Colombo",
      "company": "Kalamcx",
      "location": "Colombo, Western Province, Sri Lanka",
      "posted_date": "1 year ago",
      "job_url": "https://lk.linkedin.com/jobs/view/sinhala-vri-opi-interpretation-vacancy-colombo-at-kalamcx-3794770334?position=9&pageNum=10&refId=RmfV2i6KVltbgMmh3pQ7OQ%3D%3D&trackingId=dW5qEJo70gHM8m2OP8KzfQ%3D%3D",
      "listing_id": "urn:li:jobPosting:3794770334"
    },
    {
      "title": "Software Engineer - Frontend (React)",
      "company": "Octopus BI",
      "location": "Colombo, Western Province, Sri Lanka",
      "posted_date": "2 months ago",
      "job_url": "https://lk.linkedin.com/jobs/view/software-engineer-frontend-react-at-octopus-bi-4136357196?position=10&pageNum=10&refId=RmfV2i6KVltbgMmh3pQ7OQ%3D%3D&trackingId=FsrycK%2FrstuM74V7j8wHBg%3D%3D",
      "listing_id": "urn:li:jobPosting:4136357196"
    },
    {
      "title": "Chief Operating Officer",
      "company": "CAREER141",
      "location": "Colombo District, Western Province, Sri Lanka",
      "posted_date": "5 days ago",
      "job_url": "https://lk.linkedin.com/jobs/view/chief-operating-officer-at-career141-4192800835?position=1&pageNum=12&refId=Aj%2Bs%2F3CQFB%2FUMFUcdZuO%2BA%3D%3D&trackingId=%2FZMOh2LIAscQb%2BzGQP%2Fbqg%3D%3D",
      "listing_id": "urn:li:jobPosting:4192800835"
    },
    {
      "title": "Project Coordinator - IFS Foundation (Fixed Term Contract)",
      "company": "IFS",
      "location": "Colombo, Western Province, Sri Lanka",
      "posted_date": "1 week ago",
      "job_url": "https://lk.linkedin.com/jobs/view/project-coordinator-ifs-foundation-fixed-term-contract-at-ifs-4191720174?position=2&pageNum=12&refId=Aj%2Bs%2F3CQFB%2FUMFUcdZuO%2BA%3D%3D&trackingId=wqUXgSCaaQyR%2FJk9cfR%2F4g%3D%3D",
      "listing_id": "urn:li:jobPosting:4191720174"
    },
    {
      "title": "Squad Lead",
      "company": "Unison Consulting",
      "location": "Colombo, Western Province, Sri Lanka",
      "posted_date": "1 week ago",
      "job_url": "https://lk.linkedin.com/jobs/view/squad-lead-at-unison-consulting-4184134575?position=3&pageNum=12&refId=Aj%2Bs%2F3CQFB%2FUMFUcdZuO%2BA%3D%3D&trackingId=Z%2BSL5Ysa%2Fv8JsOQd9XskRQ%3D%3D",
      "listing_id": "urn:li:jobPosting:4184134575"
    },
    {
      "title": "EA To CEO",
      "company": "Skaleart",
      "location": "Colombo, Western Province, Sri Lanka",
      "posted_date": "1 month ago",
      "job_url": "https://lk.linkedin.com/jobs/view/ea-to-ceo-at-skaleart-4162267098?position=4&pageNum=12&refId=Aj%2Bs%2F3CQFB%2FUMFUcdZuO%2BA%3D%3D&trackingId=VAMajTzyUypo%2BtPZgAcKXQ%3D%3D",
      "listing_id": "urn:li:jobPosting:4162267098"
    },
    {
      "title": "Accounting Executive",
      "company": "Prime One Global",
      "location": "Vavuniya District, Northern Province, Sri Lanka",
      "posted_date": "2 weeks ago",
      "job_url": "https://lk.linkedin.com/jobs/view/accounting-executive-at-prime-one-global-4182846442?position=5&pageNum=12&refId=Aj%2Bs%2F3CQFB%2FUMFUcdZuO%2BA%3D%3D&trackingId=qNdsgpfi83HIVXsOqSunlw%3D%3D",
      "listing_id": "urn:li:jobPosting:4182846442"
    },
    {
      "title": "Senior Graphic Designer",
      "company": "Hype Invention",
      "location": "Colombo, Western Province, Sri Lanka",
      "posted_date": "3 months ago",
      "job_url": "https://lk.linkedin.com/jobs/view/senior-graphic-designer-at-hype-invention-4096864287?position=6&pageNum=12&refId=Aj%2Bs%2F3CQFB%2FUMFUcdZuO%2BA%3D%3D&trackingId=nKgM2Bpwl292wmNvlhlMDA%3D%3D",
      "listing_id": "urn:li:jobPosting:4096864287"
    },
    {
      "title": "Associate UI/UX Designer",
      "company": "Code94 Labs",
      "location": "Colombo, Western Province, Sri Lanka",
      "posted_date": "3 months ago",
      "job_url": "https://lk.linkedin.com/jobs/view/associate-ui-ux-designer-at-code94-labs-4104126314?position=7&pageNum=12&refId=Aj%2Bs%2F3CQFB%2FUMFUcdZuO%2BA%3D%3D&trackingId=mV9fG8YQpMcp%2FE7qdezCDw%3D%3D",
      "listing_id": "urn:li:jobPosting:4104126314"
    },
    {
      "title": "Executive - Travel Desk",
      "company": "Axiata Digital Labs",
      "location": "Colombo, Western Province, Sri Lanka",
      "posted_date": "1 month ago",
      "job_url": "https://lk.linkedin.com/jobs/view/executive-travel-desk-at-axiata-digital-labs-4141912768?position=8&pageNum=12&refId=Aj%2Bs%2F3CQFB%2FUMFUcdZuO%2BA%3D%3D&trackingId=89KyiqumoWIR%2Bv0oQ9b%2B1g%3D%3D",
      "listing_id": "urn:li:jobPosting:4141912768"
    },
    {
      "title": "Energy Adviser",
      "company": "Citizens Advice",
      "location": "Civic Centre, Northern Province, Sri Lanka",
      "posted_date": "3 days ago",
      "job_url": "https://lk.linkedin.com/jobs/view/energy-adviser-at-citizens-advice-4194412767?position=9&pageNum=12&refId=Aj%2Bs%2F3CQFB%2FUMFUcdZuO%2BA%3D%3D&trackingId=f3w5ybORRYQas89AlRx%2BZg%3D%3D",
      "listing_id": "urn:li:jobPosting:4194412767"
    },
    {
      "title": "Software Engineer",
      "company": "Transvirtual",
      "location": "Sri Lanka",
      "posted_date": "2 weeks ago",
      "job_url": "https://lk.linkedin.com/jobs/view/software-engineer-at-transvirtual-4183557019?position=10&pageNum=12&refId=Aj%2Bs%2F3CQFB%2FUMFUcdZuO%2BA%3D%3D&trackingId=qHaUqlUM7%2B6UwWgHK5zxlQ%3D%3D",
      "listing_id": "urn:li:jobPosting:4183557019"
    },
    {
      "title": "Intern - UI/UX Engineer",
      "company": "Octopus BI",
      "location": "Colombo, Western Province, Sri Lanka",
      "posted_date": "2 months ago",
      "job_url": "https://lk.linkedin.com/jobs/view/intern-ui-ux-engineer-at-octopus-bi-4136354528?position=1&pageNum=15&refId=8QR65Wn3Ot00yvYUT0h%2B0w%3D%3D&trackingId=upJ0ma9UhC8OZROmY3%2Bocg%3D%3D",
      "listing_id": "urn:li:jobPosting:4136354528"
    },
    {
      "title": "Manager- Research & Development",
      "company": "Smart Quest Consultancy",
      "location": "Gampaha District, Western Province, Sri Lanka",
      "posted_date": "1 month ago",
      "job_url": "https://lk.linkedin.com/jobs/view/manager-research-development-at-smart-quest-consultancy-4161083744?position=2&pageNum=15&refId=8QR65Wn3Ot00yvYUT0h%2B0w%3D%3D&trackingId=huhmoDpWaRgDRWuLNlhlEA%3D%3D",
      "listing_id": "urn:li:jobPosting:4161083744"
    },
    {
      "title": "Gestor(a) de Cliente",
      "company": "Clan",
      "location": "Colombo, Western Province, Sri Lanka",
      "posted_date": "1 month ago",
      "job_url": "https://lk.linkedin.com/jobs/view/gestor-a-de-cliente-at-clan-4188619760?position=3&pageNum=15&refId=8QR65Wn3Ot00yvYUT0h%2B0w%3D%3D&trackingId=HgOKwo1h%2F8Kb%2F8%2Bb%2FKDVnQ%3D%3D",
      "listing_id": "urn:li:jobPosting:4188619760"
    },
    {
      "title": "Team-Leader IT (m/f/d)",
      "company": "KRAMSKI Lanka (Pvt) Ltd.",
      "location": "Katunayake, Western Province, Sri Lanka",
      "posted_date": "1 month ago",
      "job_url": "https://lk.linkedin.com/jobs/view/team-leader-it-m-f-d-at-kramski-lanka-pvt-ltd-4143792110?position=4&pageNum=15&refId=8QR65Wn3Ot00yvYUT0h%2B0w%3D%3D&trackingId=atOW%2F03yn1V81BqI6gBGbA%3D%3D",
      "listing_id": "urn:li:jobPosting:4143792110"
    },
    {
      "title": "Team Leader Revenue",
      "company": "Otago Regional Council",
      "location": "Badulla District, Uva Province, Sri Lanka",
      "posted_date": "1 week ago",
      "job_url": "https://lk.linkedin.com/jobs/view/team-leader-revenue-at-otago-regional-council-4188486536?position=5&pageNum=15&refId=8QR65Wn3Ot00yvYUT0h%2B0w%3D%3D&trackingId=0E3Mt1v5e9hVto%2BaI3q8Iw%3D%3D",
      "listing_id": "urn:li:jobPosting:4188486536"
    },
    {
      "title": "Real Estate and Operations Manager",
      "company": "Homey",
      "location": "Colombo, Western Province, Sri Lanka",
      "posted_date": "2 months ago",
      "job_url": "https://lk.linkedin.com/jobs/view/real-estate-and-operations-manager-at-homey-4133369788?position=6&pageNum=15&refId=8QR65Wn3Ot00yvYUT0h%2B0w%3D%3D&trackingId=ikeTT5w%2FqO3Fcr%2B%2BstgwoQ%3D%3D",
      "listing_id": "urn:li:jobPosting:4133369788"
    },
    {
      "title": "Backend Developer",
      "company": "Fintechnology Asia Pacific (FINAP)",
      "location": "Colombo, Western Province, Sri Lanka",
      "posted_date": "1 month ago",
      "job_url": "https://lk.linkedin.com/jobs/view/backend-developer-at-fintechnology-asia-pacific-finap-4157153823?position=7&pageNum=15&refId=8QR65Wn3Ot00yvYUT0h%2B0w%3D%3D&trackingId=j3%2BOZ36FCdlUjdzRTpBBDg%3D%3D",
      "listing_id": "urn:li:jobPosting:4157153823"
    },
    {
      "title": "MONTEUR/ASSEMBLEUR H/F",
      "company": "Alco-TMI",
      "location": "Nuwara Eliya District, Central Province, Sri Lanka",
      "posted_date": "4 months ago",
      "job_url": "https://lk.linkedin.com/jobs/view/monteur-assembleur-h-f-at-alco-tmi-4084412308?position=8&pageNum=15&refId=8QR65Wn3Ot00yvYUT0h%2B0w%3D%3D&trackingId=3YDe1qI5UcrfYsvsxhS3kg%3D%3D",
      "listing_id": "urn:li:jobPosting:4084412308"
    },
    {
      "title": "Key User Manager_Large Users & After Sales._SriLanka",
      "company": "Bosch Electrical Drives India Private Limited (RBDI)",
      "location": "Colombo, Western Province, Sri Lanka",
      "posted_date": "4 days ago",
      "job_url": "https://lk.linkedin.com/jobs/view/key-user-manager-large-users-after-sales-srilanka-at-bosch-electrical-drives-india-private-limited-rbdi-4191160779?position=9&pageNum=15&refId=8QR65Wn3Ot00yvYUT0h%2B0w%3D%3D&trackingId=uCa8LwGaS0DXhyppGlZVbQ%3D%3D",
      "listing_id": "urn:li:jobPosting:4191160779"
    },
    {
      "title": "Intern Software Engineering (PHP & Node.js)",
      "company": "Konekt - Technology Solutions Provider",
      "location": "Colombo, Western Province, Sri Lanka",
      "posted_date": "3 months ago",
      "job_url": "https://lk.linkedin.com/jobs/view/intern-software-engineering-php-node-js-at-konekt-technology-solutions-provider-4095506382?position=10&pageNum=15&refId=8QR65Wn3Ot00yvYUT0h%2B0w%3D%3D&trackingId=c%2FPmHaaIoxf8Z5oQcZhZ3w%3D%3D",
      "listing_id": "urn:li:jobPosting:4095506382"
    }
  ]
}